tests/test_benchmark.py
tests/test_ffmpeg_features.py
tests/test_roundtrip.py
videoparquet/__init__.py
videoparquet/ffmpeg_wrappers.py
videoparquet/get_recipe.py
videoparquet/metadata.py
videoparquet/parquet2video.py
videoparquet/utils.py
videoparquet/video2parquet.py
videoparquet-0.1.1.dist-info/METADATA
videoparquet-0.1.1.dist-info/WHEEL
videoparquet-0.1.1.dist-info/top_level.txt
videoparquet-0.1.1.dist-info/RECORD
