Metadata-Version: 2.4
Name: videoparquet
Version: 0.1.1
Summary: Convert Parquet files to video and back, inspired by xarrayvideo
Home-page: https://github.com/yourusername/videoparquet
Author: Your Name
Author-email: Your Name <your.email@example.com>
License: MIT
Project-URL: Documentation, https://github.com/yourusername/videoparquet
Project-URL: Source, https://github.com/yourusername/videoparquet
Project-URL: Tracker, https://github.com/yourusername/videoparquet/issues
Keywords: parquet,video,ffmpeg,scientific-data,compression
Classifier: Programming Language :: Python :: 3
Classifier: License :: OSI Approved :: MIT License
Classifier: Operating System :: OS Independent
Classifier: Intended Audience :: Science/Research
Classifier: Topic :: Scientific/Engineering :: Information Analysis
Classifier: Topic :: Multimedia :: Video
Classifier: Development Status :: 3 - Alpha
Requires-Python: >=3.7
Requires-Dist: pyarrow
Requires-Dist: pandas
Requires-Dist: numpy
Requires-Dist: ffmpeg-python
Requires-Dist: scikit-learn
Provides-Extra: dev
Requires-Dist: pytest; extra == "dev"
Requires-Dist: twine; extra == "dev"
Requires-Dist: build; extra == "dev"
Dynamic: author
Dynamic: home-page
Dynamic: requires-python
